pywalc/__init__.py
pywalc/__main__.py
pywalc/app.py
pywalc/colors.py
pywalc/pywal_util.py
pywalc/server.py
pywalc/settings.py
pywalc/theme.py
pywalc/util.py
pywalc/wallpaper.py
pywalc/static/css/style.css
pywalc/static/js/Actions.js
pywalc/static/js/Color.js
pywalc/static/js/Sys.js
pywalc/static/js/Theme.js
pywalc/static/js/Wallpaper.js
pywalc/static/js/api.js
pywalc/static/js/data.js
pywalc/static/js/helper.js
pywalc/static/js/main.js
pywalc/templates/index.html
pywalc-0.2.1.dist-info/LICENSE
pywalc-0.2.1.dist-info/METADATA
pywalc-0.2.1.dist-info/WHEEL
pywalc-0.2.1.dist-info/entry_points.txt
pywalc-0.2.1.dist-info/top_level.txt
pywalc-0.2.1.dist-info/RECORD
