Metadata-Version: 2.1
Name: pywalc
Version: 0.2.1
Summary: Change pywal color online
Home-page: https://github.com/png261/pywalc
Download-URL: https://github.com/png261/pywalc/archive/0.2.1.tar.gz
Author: Phuong Nguyen
Author-email: nhphuong.code@gmail.com
License: MIT
Keywords: pywalc wal colorscheme terminal-emulators changing-colorschemes
Classifier: Environment :: X11 Applications
Classifier: License :: OSI Approved :: MIT License
Classifier: Operating System :: POSIX :: Linux
Classifier: Programming Language :: Python :: 3.5
Classifier: Programming Language :: Python :: 3.6
Requires-Python: >=3.5
License-File: LICENSE
Requires-Dist: pywal (>=3.3.0)
Requires-Dist: fastapi (>=0.97.0)
Requires-Dist: uvicorn (>=0.22.0)
Requires-Dist: pycloudflared (>=0.2.0)
Requires-Dist: Jinja2 (>=3.1.2)
Requires-Dist: python-multipart (>=0.0.6)
Requires-Dist: qrcode (>=7.4.2)
Requires-Dist: argparse (>=1.4.0)
